six.py
google/__init__.py
google/protobuf_ml/__init__.py
google/protobuf_ml/descriptor.py
google/protobuf_ml/descriptor_database.py
google/protobuf_ml/descriptor_pb2.py
google/protobuf_ml/descriptor_pool.py
google/protobuf_ml/json_format.py
google/protobuf_ml/message.py
google/protobuf_ml/message_factory.py
google/protobuf_ml/proto_builder.py
google/protobuf_ml/reflection.py
google/protobuf_ml/service.py
google/protobuf_ml/service_reflection.py
google/protobuf_ml/symbol_database.py
google/protobuf_ml/text_encoding.py
google/protobuf_ml/text_format.py
google/protobuf_ml/unknown_fields.py
google/protobuf_ml/internal/__init__.py
google/protobuf_ml/internal/_parameterized.py
google/protobuf_ml/internal/api_implementation.py
google/protobuf_ml/internal/builder.py
google/protobuf_ml/internal/containers.py
google/protobuf_ml/internal/decoder.py
google/protobuf_ml/internal/descriptor_database_test.py
google/protobuf_ml/internal/descriptor_pool_test.py
google/protobuf_ml/internal/descriptor_test.py
google/protobuf_ml/internal/encoder.py
google/protobuf_ml/internal/enum_type_wrapper.py
google/protobuf_ml/internal/extension_dict.py
google/protobuf_ml/internal/field_mask.py
google/protobuf_ml/internal/field_mask_test.py
google/protobuf_ml/internal/generator_test.py
google/protobuf_ml/internal/import_test.py
google/protobuf_ml/internal/json_format_test.py
google/protobuf_ml/internal/keywords_test.py
google/protobuf_ml/internal/message_factory_test.py
google/protobuf_ml/internal/message_listener.py
google/protobuf_ml/internal/message_test.py
google/protobuf_ml/internal/proto_builder_test.py
google/protobuf_ml/internal/python_edition_defaults.py
google/protobuf_ml/internal/python_message.py
google/protobuf_ml/internal/reflection_test.py
google/protobuf_ml/internal/service_reflection_test.py
google/protobuf_ml/internal/symbol_database_test.py
google/protobuf_ml/internal/test_util.py
google/protobuf_ml/internal/testing_refleaks.py
google/protobuf_ml/internal/text_encoding_test.py
matlab_prodserver_client-25.2.dist-info/licenses/LICENSE.txt
matlab_prodserver_client-25.2.dist-info/METADATA
matlab_prodserver_client-25.2.dist-info/WHEEL
matlab_prodserver_client-25.2.dist-info/top_level.txt
matlab_prodserver_client-25.2.dist-info/RECORD
