Metadata-Version: 2.4
Name: matlab-prodserver-client
Version: 25.2
Summary: A package to invoke MATLAB functions, deployed on MATLAB Production Server, from Python
Home-page: https://www.mathworks.com/
Author: MathWorks, Inc.
License: BSD License (Copyright (c) 2025, The MathWorks, Inc.
Platform: Linux
Platform: Windows
Platform: macOS
License-File: LICENSE.txt
Dynamic: author
Dynamic: description
Dynamic: description-content-type
Dynamic: home-page
Dynamic: license
Dynamic: license-file
Dynamic: platform
Dynamic: summary
